Metadata-Version: 2.1
Name: trebasiccalculator
Version: 0.0.1
Summary: A basic calculator
Home-page: 
Author: Tre Robinson
Author-email: trerrobinson@gmail.com
License: MIT
Classifier: Intended Audience :: Education
Classifier: Operating System :: MacOS
Classifier: License :: OSI Approved :: MIT License
Classifier: Programming Language :: Python :: 3
License-File: LICENSE
